{"preview_id": "705cc69ab26c419087b1b864fe835353", "image_filename": "image (13).png", "folder_path": "D:\\AI\\assets", "title": "Image (13)", "caption": "You're overpaying for tech and you don't even know it. 😤\n\nStyleus.co.in specials are live — handpicked deals you won't find anywhere else.\nWhether it's gadgets, accessories, or the latest gear, we've sorted it all for you.\nStop jumping between random sites. One place, best prices, zero hassle.\n\nCheck the link in bio and grab yours before it's gone.\n\n#Styleus #StyleusCoIn #IndianTechMarketplace #TechDealsIndia #GadgetsIndia #OnlineShoppingIndia #TechSpecials #IndianGadgets #BestTechDeals #IndianStartup #TechShopping #Indiatech", "caption_body": "You're overpaying for tech and you don't even know it. 😤\n\nStyleus.co.in specials are live — handpicked deals you won't find anywhere else.\nWhether it's gadgets, accessories, or the latest gear, we've sorted it all for you.\nStop jumping between random sites. One place, best prices, zero hassle.\n\nCheck the link in bio and grab yours before it's gone.", "hook": "You're overpaying for tech and you don't even know it. 😤", "hashtags": ["#Styleus", "#StyleusCoIn", "#IndianTechMarketplace", "#TechDealsIndia", "#GadgetsIndia", "#OnlineShoppingIndia", "#TechSpecials", "#IndianGadgets", "#BestTechDeals", "#IndianStartup", "#TechShopping", "#Indiatech"]}